epicAI/__init__.py
epicAI/agent_action.py
epicAI/api_client.py
epicAI/auth.py
epicAI/mini_notebook.py
sagebow/__init__.py
sagebow/core.py
sagebow-0.1.1.dist-info/METADATA
sagebow-0.1.1.dist-info/WHEEL
sagebow-0.1.1.dist-info/entry_points.txt
sagebow-0.1.1.dist-info/top_level.txt
sagebow-0.1.1.dist-info/RECORD
